scimesh/__init__.py
scimesh/_version.py
scimesh/cache.py
scimesh/cli.py
scimesh/exceptions.py
scimesh/fulltext.py
scimesh/models.py
scimesh/py.typed
scimesh/search.py
scimesh/throttle.py
scimesh/download/__init__.py
scimesh/download/base.py
scimesh/download/fallback.py
scimesh/download/host_concurrency.py
scimesh/download/openaccess.py
scimesh/download/scihub.py
scimesh/export/__init__.py
scimesh/export/base.py
scimesh/export/bibtex.py
scimesh/export/csv.py
scimesh/export/json.py
scimesh/export/ris.py
scimesh/export/tree.py
scimesh/export/vault.py
scimesh/providers/__init__.py
scimesh/providers/_fulltext_fallback.py
scimesh/providers/arxiv.py
scimesh/providers/base.py
scimesh/providers/openalex.py
scimesh/providers/scopus.py
scimesh/providers/semantic_scholar.py
scimesh/query/__init__.py
scimesh/query/combinators.py
scimesh/query/parser.py
scimesh/vault/__init__.py
scimesh/vault/cli.py
scimesh/vault/models.py
scimesh/vault/operations.py
scimesh-0.2.3.dist-info/METADATA
scimesh-0.2.3.dist-info/WHEEL
scimesh-0.2.3.dist-info/entry_points.txt
scimesh-0.2.3.dist-info/licenses/LICENSE
scimesh-0.2.3.dist-info/RECORD
