Metadata-Version: 2.4
Name: scimesh
Version: 0.2.3
Summary: Systematic literature search library for scientific papers
Project-URL: Homepage, https://github.com/gabfssilva/scimesh
Project-URL: Repository, https://github.com/gabfssilva/scimesh
Project-URL: Documentation, https://github.com/gabfssilva/scimesh#readme
Author-email: Gabriel Francisco <gabfssilva@gmail.com>
License-Expression: MIT
License-File: LICENSE
Keywords: arxiv,bibtex,literature,openalex,papers,research,scientific,scopus,search
Classifier: Development Status :: 4 - Beta
Classifier: Intended Audience :: Science/Research
Classifier: License :: OSI Approved :: MIT License
Classifier: Programming Language :: Python :: 3.12
Classifier: Programming Language :: Python :: 3.13
Classifier: Programming Language :: Python :: 3.14
Classifier: Topic :: Scientific/Engineering
Classifier: Topic :: Text Processing :: Indexing
Classifier: Typing :: Typed
Requires-Python: >=3.12
Requires-Dist: cyclopts>=4.5.1
Requires-Dist: httpx>=0.28.1
Requires-Dist: pymupdf4llm>=0.2.9
Requires-Dist: pyyaml>=6.0
Requires-Dist: streamish>=0.1.0
Requires-Dist: tenacity>=9.1.2
